anixartpy/__init__.py
anixartpy/anix_images.py
anixartpy/enums.py
anixartpy/errors.py
anixartpy/utils.py
anixartpy/models/__init__.py
anixartpy/models/article.py
anixartpy/models/articleSuggestion.py
anixartpy/models/base.py
anixartpy/models/channel.py
anixartpy/models/comment.py
anixartpy/models/payload.py
anixartpy/models/profile.py
anixartpy/models/user_vote.py
anixartpy-0.4.4.dist-info/licenses/LICENSE
anixartpy-0.4.4.dist-info/METADATA
anixartpy-0.4.4.dist-info/WHEEL
anixartpy-0.4.4.dist-info/top_level.txt
anixartpy-0.4.4.dist-info/RECORD
