Metadata-Version: 2.4
Name: anixartpy
Version: 0.4.4
Summary: Python-оболочка для API Anixart
Home-page: https://github.com/PartyCorn/anixartpy
Author: Andrew Kurilov (PartyCorn)
Author-email: partycorn.00@mail.ru
License: MIT
Classifier: License :: OSI Approved :: MIT License
Classifier: Programming Language :: Python :: 3
Classifier: Programming Language :: Python :: 3.8
Classifier: Programming Language :: Python :: 3.9
Classifier: Programming Language :: Python :: 3.10
Requires-Python: >=3.8
License-File: LICENSE
Requires-Dist: requests>=2.25.0
Requires-Dist: typing-extensions>=3.7.4
Dynamic: license-file
